LGPy/Hardware.py
LGPy/Instructions.py
LGPy/Mutation.py
LGPy/Selection.py
LGPy/__init__.py
LGPy-1.0.2.dist-info/LICENSE
LGPy-1.0.2.dist-info/METADATA
LGPy-1.0.2.dist-info/WHEEL
LGPy-1.0.2.dist-info/top_level.txt
LGPy-1.0.2.dist-info/RECORD
