Metadata-Version: 2.1
Name: LGPy
Version: 1.0.2
Summary: A Linear Genetic Programming Library
Home-page: https://github.com/nateriz/lgpy
Author: NateRiz
Author-email: nathan.rizik@gmail.com
License: UNKNOWN
Platform: UNKNOWN
Classifier: Programming Language :: Python :: 3
Classifier: License :: OSI Approved :: GNU General Public License v3 (GPLv3)
Classifier: Operating System :: OS Independent
Requires-Python: >=3.6
